hashsmith-0.2.2.dist-info/METADATA
hashsmith-0.2.2.dist-info/WHEEL
hashsmith-0.2.2.dist-info/entry_points.txt
hashsmith-0.2.2.dist-info/licenses/LICENSE
hashsmith/__init__.py
hashsmith/attacks/__init__.py
hashsmith/attacks/dictionary_attack.py
hashsmith/core/__init__.py
hashsmith/core/hashcat_runner.py
hashsmith/core/session_manager.py
hashsmith/patterns/__init__.py
hashsmith/patterns/engine.py
hashsmith-0.2.2.dist-info/RECORD
