Metadata-Version: 2.1
Name: hashsmith
Version: 0.2.2
Summary: A modern, compositional password pattern engine and hashcat orchestrator
Keywords: password,hashcat,security,patterns,cracking,wordlist
Author-Email: Baksi Li <myself@baksili.codes>
License: MIT
Classifier: Development Status :: 3 - Alpha
Classifier: Environment :: Console
Classifier: Intended Audience :: Developers
Classifier: Intended Audience :: Information Technology
Classifier: License :: OSI Approved :: MIT License
Classifier: Programming Language :: Python :: 3
Classifier: Programming Language :: Python :: 3.11
Classifier: Programming Language :: Python :: 3.12
Classifier: Topic :: Security
Classifier: Topic :: Security :: Cryptography
Classifier: Topic :: Utilities
Project-URL: Homepage, https://github.com/BaksiLi/hashsmith
Project-URL: Issues, https://github.com/BaksiLi/hashsmith/issues
Project-URL: Documentation, https://github.com/BaksiLi/hashsmith#readme
Requires-Python: >=3.11
Requires-Dist: pycryptodome>=3.23.0
Requires-Dist: pysodium>=0.7.18
